{"id":"8t3swuswoi81yuzo2bnecy9","title":"flow snapshot","desc":"","updated":1756869568794,"created":1751689346769,"custom":{},"fname":"mesh-resource.node-component.flow-snapshot","type":"note","vault":{"fsPath":"documentation","selfContained":false,"name":"sflo"},"contentHash":"d68485219773bd289829edf66dbdf7c2","links":[{"type":"wiki","from":{"fname":"mesh-resource.node-component.flow-snapshot","id":"8t3swuswoi81yuzo2bnecy9","vaultName":"sflo"},"value":"mesh-resource.node-component.flow","position":{"start":{"line":2,"column":97,"offset":97},"end":{"line":2,"column":134,"offset":134},"indent":[]},"xvault":false,"sameFile":false,"to":{"fname":"mesh-resource.node-component.flow"}},{"type":"wiki","from":{"fname":"mesh-resource.node-component.flow-snapshot","id":"8t3swuswoi81yuzo2bnecy9","vaultName":"sflo"},"value":"mesh-resource.node-component.snapshot-distribution","alias":"distributions","position":{"start":{"line":4,"column":35,"offset":173},"end":{"line":4,"column":103,"offset":241},"indent":[]},"xvault":false,"sameFile":false,"to":{"fname":"mesh-resource.node-component.snapshot-distribution"}},{"type":"wiki","from":{"fname":"mesh-resource.node-component.flow-snapshot","id":"8t3swuswoi81yuzo2bnecy9","vaultName":"sflo"},"value":"mesh-resource.node-component.flow","position":{"start":{"line":8,"column":51,"offset":404},"end":{"line":8,"column":88,"offset":441},"indent":[]},"xvault":false,"sameFile":false,"to":{"fname":"mesh-resource.node-component.flow"}},{"type":"wiki","from":{"fname":"mesh-resource.node-component.flow-snapshot","id":"8t3swuswoi81yuzo2bnecy9","vaultName":"sflo"},"value":"mesh-resource.node-component.flow-snapshot.version","position":{"start":{"line":63,"column":3,"offset":2253},"end":{"line":63,"column":57,"offset":2307},"indent":[]},"xvault":false,"sameFile":false,"to":{"fname":"mesh-resource.node-component.flow-snapshot.version"}},{"type":"wiki","from":{"fname":"mesh-resource.node-component.flow-snapshot","id":"8t3swuswoi81yuzo2bnecy9","vaultName":"sflo"},"value":"mesh-resource.node-component.flow-snapshot.current","position":{"start":{"line":65,"column":3,"offset":2531},"end":{"line":65,"column":57,"offset":2585},"indent":[]},"xvault":false,"sameFile":false,"to":{"fname":"mesh-resource.node-component.flow-snapshot.current"}},{"type":"wiki","from":{"fname":"mesh-resource.node-component.flow-snapshot","id":"8t3swuswoi81yuzo2bnecy9","vaultName":"sflo"},"value":"mesh-resource.node-component.flow-snapshot.next","position":{"start":{"line":65,"column":188,"offset":2716},"end":{"line":65,"column":239,"offset":2767},"indent":[]},"xvault":false,"sameFile":false,"to":{"fname":"mesh-resource.node-component.flow-snapshot.next"}},{"type":"wiki","from":{"fname":"mesh-resource.node-component.flow-snapshot","id":"8t3swuswoi81yuzo2bnecy9","vaultName":"sflo"},"value":"mesh-resource.node-component.flow-snapshot.next","position":{"start":{"line":67,"column":3,"offset":2785},"end":{"line":67,"column":54,"offset":2836},"indent":[]},"xvault":false,"sameFile":false,"to":{"fname":"mesh-resource.node-component.flow-snapshot.next"}},{"type":"wiki","from":{"fname":"mesh-resource.node-component.flow-snapshot","id":"8t3swuswoi81yuzo2bnecy9","vaultName":"sflo"},"value":"concept.weave","position":{"start":{"line":75,"column":70,"offset":3166},"end":{"line":75,"column":87,"offset":3183},"indent":[]},"xvault":false,"sameFile":false,"to":{"fname":"concept.weave"}},{"type":"wiki","from":{"fname":"mesh-resource.node-component.flow-snapshot","id":"8t3swuswoi81yuzo2bnecy9","vaultName":"sflo"},"value":"mesh-resource.node-component.flow","position":{"start":{"line":80,"column":5,"offset":3276},"end":{"line":80,"column":42,"offset":3313},"indent":[]},"xvault":false,"sameFile":false,"to":{"fname":"mesh-resource.node-component.flow"}},{"type":"wiki","from":{"fname":"mesh-resource.node-component.flow-snapshot","id":"8t3swuswoi81yuzo2bnecy9","vaultName":"sflo"},"value":"concept.versioning","position":{"start":{"line":81,"column":5,"offset":3349},"end":{"line":81,"column":27,"offset":3371},"indent":[]},"xvault":false,"sameFile":false,"to":{"fname":"concept.versioning"}},{"type":"wiki","from":{"fname":"mesh-resource.node-component.flow-snapshot","id":"8t3swuswoi81yuzo2bnecy9","vaultName":"sflo"},"value":"concept.weave-process","position":{"start":{"line":82,"column":5,"offset":3425},"end":{"line":82,"column":30,"offset":3450},"indent":[]},"xvault":false,"sameFile":false,"to":{"fname":"concept.weave-process"}},{"from":{"fname":"concept.mesh","id":"h6ssv16gdyf56gg235dxv85","vaultName":"sflo"},"type":"backlink","position":{"start":{"line":76,"column":55,"offset":6061},"end":{"line":76,"column":101,"offset":6107},"indent":[]},"value":"mesh-resource.node-component.flow-snapshot"},{"from":{"fname":"concept.summary","id":"concept-summary","vaultName":"sflo"},"type":"backlink","position":{"start":{"line":45,"column":17,"offset":2390},"end":{"line":45,"column":63,"offset":2436},"indent":[]},"value":"mesh-resource.node-component.flow-snapshot"},{"from":{"fname":"concept.summary","id":"concept-summary","vaultName":"sflo"},"type":"backlink","position":{"start":{"line":210,"column":3,"offset":9976},"end":{"line":210,"column":49,"offset":10022},"indent":[]},"value":"mesh-resource.node-component.flow-snapshot"},{"from":{"fname":"faq.why-dont-data-nodes-contain-distributions-directly","id":"osqi7xn4mw3j9v0kvsoc5uo","vaultName":"sflo"},"type":"backlink","position":{"start":{"line":47,"column":5,"offset":2043},"end":{"line":47,"column":51,"offset":2089},"indent":[]},"value":"mesh-resource.node-component.flow-snapshot"},{"from":{"fname":"folder._current","id":"xz41kd5hzao6yjybm05uw4l","vaultName":"sflo"},"type":"backlink","position":{"start":{"line":2,"column":6,"offset":6},"end":{"line":2,"column":52,"offset":52},"indent":[]},"value":"mesh-resource.node-component.flow-snapshot"},{"from":{"fname":"guide.project-brief","id":"p1h6n78assy929ogf6e97uy","vaultName":"sflo"},"type":"backlink","position":{"start":{"line":17,"column":3,"offset":676},"end":{"line":17,"column":49,"offset":722},"indent":[]},"value":"mesh-resource.node-component.flow-snapshot"},{"from":{"fname":"facet.filesystem.folder","id":"p3mbdrze0qe8uvko4i16t1s","vaultName":"sflo"},"type":"backlink","position":{"start":{"line":34,"column":45,"offset":1004},"end":{"line":34,"column":91,"offset":1050},"indent":[]},"value":"mesh-resource.node-component.flow-snapshot"},{"from":{"fname":"facet.resource.dataset","id":"6ki4upsdymjb9vy82oec2cf","vaultName":"sflo"},"type":"backlink","position":{"start":{"line":7,"column":39,"offset":356},"end":{"line":7,"column":85,"offset":402},"indent":[]},"value":"mesh-resource.node-component.flow-snapshot"},{"from":{"fname":"facet.resource.dataset","id":"6ki4upsdymjb9vy82oec2cf","vaultName":"sflo"},"type":"backlink","position":{"start":{"line":12,"column":3,"offset":1230},"end":{"line":12,"column":49,"offset":1276},"indent":[]},"value":"mesh-resource.node-component.flow-snapshot"},{"from":{"fname":"mesh-resource.node-component.aggregated-distribution","id":"e6enrj5ztz3hz84ojujef0k","vaultName":"sflo"},"type":"backlink","position":{"start":{"line":79,"column":5,"offset":3114},"end":{"line":79,"column":51,"offset":3160},"indent":[]},"value":"mesh-resource.node-component.flow-snapshot"},{"from":{"fname":"mesh-resource.node-component.flow","id":"node-flow","vaultName":"sflo"},"type":"backlink","position":{"start":{"line":15,"column":51,"offset":739},"end":{"line":15,"column":97,"offset":785},"indent":[]},"value":"mesh-resource.node-component.flow-snapshot"},{"from":{"fname":"mesh-resource.node-component.snapshot-distribution","id":"0n1lq6aq1gskj46bpcx9h4h","vaultName":"sflo"},"type":"backlink","position":{"start":{"line":2,"column":8,"offset":8},"end":{"line":2,"column":54,"offset":54},"indent":[]},"value":"mesh-resource.node-component.flow-snapshot"},{"from":{"fname":"mesh-resource.node.payload","id":"payload-node","vaultName":"sflo"},"type":"backlink","position":{"start":{"line":12,"column":8,"offset":849},"end":{"line":12,"column":69,"offset":910},"indent":[]},"value":"mesh-resource.node-component.flow-snapshot"},{"from":{"fname":"mesh-resource.node-component.flow.payload","id":"payload-flow","vaultName":"sflo"},"type":"backlink","position":{"start":{"line":21,"column":40,"offset":993},"end":{"line":21,"column":101,"offset":1054},"indent":[]},"value":"mesh-resource.node-component.flow-snapshot"},{"from":{"fname":"mesh-resource.node-component.flow.payload","id":"payload-flow","vaultName":"sflo"},"type":"backlink","position":{"start":{"line":31,"column":6,"offset":1444},"end":{"line":31,"column":66,"offset":1504},"indent":[]},"value":"mesh-resource.node-component.flow-snapshot"},{"from":{"fname":"mesh-resource.node-component.snapshot-distribution.working","id":"2qp8vfjygd43lmwcmj6362r","vaultName":"sflo"},"type":"backlink","position":{"start":{"line":2,"column":19,"offset":19},"end":{"line":2,"column":65,"offset":65},"indent":[]},"value":"mesh-resource.node-component.flow-snapshot"}],"anchors":{"relationship-to-node-flows":{"type":"header","text":"Relationship to node flows","value":"relationship-to-node-flows","line":12,"column":0,"depth":2},"relationship-pattern":{"type":"header","text":"Relationship pattern:","value":"relationship-pattern","line":16,"column":0,"depth":3},"ontology-dataset-node-example":{"type":"header","text":"Ontology dataset node Example","value":"ontology-dataset-node-example","line":24,"column":0,"depth":3},"temporal-nature":{"type":"header","text":"Temporal Nature","value":"temporal-nature","line":44,"column":0,"depth":2},"content-structure":{"type":"header","text":"Content Structure","value":"content-structure","line":52,"column":0,"depth":2},"example-structure":{"type":"header","text":"Example Structure","value":"example-structure","line":59,"column":0,"depth":3},"immutability":{"type":"header","text":"Immutability","value":"immutability","line":67,"column":0,"depth":2},"creation-and-lifecycle":{"type":"header","text":"Creation and Lifecycle","value":"creation-and-lifecycle","line":77,"column":0,"depth":2},"related-concepts":{"type":"header","text":"Related Concepts","value":"related-concepts","line":84,"column":0,"depth":2}},"children":["074yxm151l47n1aak58ggni","yci31i07s3bwpl9jd2hptod","r6akf3zjimf3ubkxpqmeubc"],"parent":"9c27yly4ed3ju7msf8luhge","data":{}}
