{"id":"loygbgsnn26c4shdayxaofe","title":"Resource Fragment","desc":"","updated":1756869020429,"created":1752244988548,"custom":{},"fname":"mesh-resource.node-component.documentation-resource.resource-fragment","type":"note","vault":{"fsPath":"documentation","selfContained":false,"name":"sflo"},"contentHash":"23bdc55f78f01b8302c46c365e33d08f","links":[{"type":"wiki","from":{"fname":"mesh-resource.node-component.documentation-resource.resource-fragment","id":"loygbgsnn26c4shdayxaofe","vaultName":"sflo"},"value":"product.service.design.htmx","position":{"start":{"line":2,"column":24,"offset":24},"end":{"line":2,"column":55,"offset":55},"indent":[]},"xvault":false,"sameFile":false,"to":{"fname":"product.service.design.htmx"}},{"type":"wiki","from":{"fname":"mesh-resource.node-component.documentation-resource.resource-fragment","id":"loygbgsnn26c4shdayxaofe","vaultName":"sflo"},"value":"mesh-resource.node-component.documentation-resource.resource-page","position":{"start":{"line":2,"column":96,"offset":96},"end":{"line":2,"column":165,"offset":165},"indent":[]},"xvault":false,"sameFile":false,"to":{"fname":"mesh-resource.node-component.documentation-resource.resource-page"}},{"from":{"fname":"concept.summary","id":"concept-summary","vaultName":"sflo"},"type":"backlink","position":{"start":{"line":57,"column":26,"offset":3356},"end":{"line":57,"column":99,"offset":3429},"indent":[]},"value":"mesh-resource.node-component.documentation-resource.resource-fragment"}],"anchors":{"multiple-resource-fragments-in-assets":{"type":"header","text":"Multiple Resource Fragments in Assets","value":"multiple-resource-fragments-in-assets","line":16,"column":0,"depth":2}},"children":[],"parent":"kjv2s38gz9xxk94szui293p","data":{}}
