{"id":"rregmt56znauz71qgypet6a","title":"node flow","desc":"","updated":1752025335642,"created":1751688486456,"custom":{},"fname":"concept.mesh.resource.element.flow","type":"note","vault":{"fsPath":"documentation","selfContained":false,"name":"sflo"},"contentHash":"599c07b19d107457a871f4a3f013097c","links":[{"type":"wiki","from":{"fname":"concept.mesh.resource.element.flow","id":"rregmt56znauz71qgypet6a","vaultName":"sflo"},"value":"concept.mesh.resource.element.flow.snapshot","position":{"start":{"line":12,"column":51,"offset":649},"end":{"line":12,"column":98,"offset":696},"indent":[]},"xvault":false,"sameFile":false,"to":{"fname":"concept.mesh.resource.element.flow.snapshot"}},{"type":"wiki","from":{"fname":"concept.mesh.resource.element.flow","id":"rregmt56znauz71qgypet6a","vaultName":"sflo"},"value":"concept.mesh.resource.element.flow.snapshot.current","position":{"start":{"line":16,"column":51,"offset":936},"end":{"line":16,"column":106,"offset":991},"indent":[]},"xvault":false,"sameFile":false,"to":{"fname":"concept.mesh.resource.element.flow.snapshot.current"}},{"type":"wiki","from":{"fname":"concept.mesh.resource.element.flow","id":"rregmt56znauz71qgypet6a","vaultName":"sflo"},"value":"concept.mesh.resource.element.flow.snapshot.next","position":{"start":{"line":16,"column":111,"offset":996},"end":{"line":16,"column":163,"offset":1048},"indent":[]},"xvault":false,"sameFile":false,"to":{"fname":"concept.mesh.resource.element.flow.snapshot.next"}},{"type":"wiki","from":{"fname":"concept.mesh.resource.element.flow","id":"rregmt56znauz71qgypet6a","vaultName":"sflo"},"value":"related-topics.dcat.dataset-series","position":{"start":{"line":18,"column":20,"offset":1070},"end":{"line":18,"column":58,"offset":1108},"indent":[]},"xvault":false,"sameFile":false,"to":{"fname":"related-topics.dcat.dataset-series"}},{"type":"wiki","from":{"fname":"concept.mesh.resource.element.flow","id":"rregmt56znauz71qgypet6a","vaultName":"sflo"},"value":"concept.mesh.resource.element.flow.snapshot.version","position":{"start":{"line":18,"column":103,"offset":1153},"end":{"line":18,"column":158,"offset":1208},"indent":[]},"xvault":false,"sameFile":false,"to":{"fname":"concept.mesh.resource.element.flow.snapshot.version"}},{"from":{"fname":"concept.mesh","id":"h6ssv16gdyf56gg235dxv85","vaultName":"sflo"},"type":"backlink","position":{"start":{"line":9,"column":103,"offset":605},"end":{"line":9,"column":141,"offset":643},"indent":[]},"value":"concept.mesh.resource.element.flow"},{"from":{"fname":"concept.mesh","id":"h6ssv16gdyf56gg235dxv85","vaultName":"sflo"},"type":"backlink","position":{"start":{"line":33,"column":5,"offset":1673},"end":{"line":33,"column":43,"offset":1711},"indent":[]},"value":"concept.mesh.resource.element.flow"},{"from":{"fname":"concept.versioning","id":"m24m2p2s7iom3rwzvp28kvy","vaultName":"sflo"},"type":"backlink","position":{"start":{"line":2,"column":6,"offset":6},"end":{"line":2,"column":44,"offset":44},"indent":[]},"value":"concept.mesh.resource.element.flow"},{"from":{"fname":"concept.mesh.flow-facet.deversioned","id":"20dz80zbx82nrym7e88ozy7","vaultName":"sflo"},"type":"backlink","position":{"start":{"line":2,"column":29,"offset":29},"end":{"line":2,"column":67,"offset":67},"indent":[]},"value":"concept.mesh.resource.element.flow"},{"from":{"fname":"concept.mesh.flow-facet.versioned","id":"elncscz2versnfcbtvqsg46","vaultName":"sflo"},"type":"backlink","position":{"start":{"line":2,"column":3,"offset":3},"end":{"line":2,"column":41,"offset":41},"indent":[]},"value":"concept.mesh.resource.element.flow"},{"from":{"fname":"concept.mesh.resource-facet.dataset","id":"6ki4upsdymjb9vy82oec2cf","vaultName":"sflo"},"type":"backlink","position":{"start":{"line":5,"column":5,"offset":136},"end":{"line":5,"column":43,"offset":174},"indent":[]},"value":"concept.mesh.resource.element.flow"},{"from":{"fname":"concept.mesh.resource.element","id":"9c27yly4ed3ju7msf8luhge","vaultName":"sflo"},"type":"backlink","position":{"start":{"line":14,"column":42,"offset":635},"end":{"line":14,"column":80,"offset":673},"indent":[]},"value":"concept.mesh.resource.element.flow"},{"from":{"fname":"concept.mesh.resource.element","id":"9c27yly4ed3ju7msf8luhge","vaultName":"sflo"},"type":"backlink","position":{"start":{"line":22,"column":115,"offset":1113},"end":{"line":22,"column":153,"offset":1151},"indent":[]},"value":"concept.mesh.resource.element.flow"},{"from":{"fname":"concept.mesh.resource.element.handle","id":"o2926clbf63vi9kln79kapg","vaultName":"sflo"},"type":"backlink","position":{"start":{"line":10,"column":136,"offset":684},"end":{"line":10,"column":174,"offset":722},"indent":[]},"value":"concept.mesh.resource.element.flow"},{"from":{"fname":"concept.mesh.resource.node.data","id":"8hmkiyjtsey7z8y5oi5xdxx","vaultName":"sflo"},"type":"backlink","position":{"start":{"line":4,"column":194,"offset":207},"end":{"line":4,"column":232,"offset":245},"indent":[]},"value":"concept.mesh.resource.element.flow"},{"from":{"fname":"concept.mesh.resource.element.flow.data","id":"9j8lhoyb0xkhg926nafgkai","vaultName":"sflo"},"type":"backlink","position":{"start":{"line":4,"column":35,"offset":48},"end":{"line":4,"column":84,"offset":97},"indent":[]},"value":"concept.mesh.resource.element.flow"},{"from":{"fname":"concept.mesh.resource.element.flow.snapshot","id":"8t3swuswoi81yuzo2bnecy9","vaultName":"sflo"},"type":"backlink","position":{"start":{"line":2,"column":96,"offset":96},"end":{"line":2,"column":134,"offset":134},"indent":[]},"value":"concept.mesh.resource.element.flow"},{"from":{"fname":"concept.mesh.resource.element.flow.snapshot","id":"8t3swuswoi81yuzo2bnecy9","vaultName":"sflo"},"type":"backlink","position":{"start":{"line":8,"column":51,"offset":564},"end":{"line":8,"column":89,"offset":602},"indent":[]},"value":"concept.mesh.resource.element.flow"},{"from":{"fname":"concept.mesh.resource.element.flow.snapshot","id":"8t3swuswoi81yuzo2bnecy9","vaultName":"sflo"},"type":"backlink","position":{"start":{"line":86,"column":5,"offset":3852},"end":{"line":86,"column":43,"offset":3890},"indent":[]},"value":"concept.mesh.resource.element.flow"},{"from":{"fname":"concept.mesh.resource.element.flow.unified","id":"sif626tmt3mw3nir5gv1s1a","vaultName":"sflo"},"type":"backlink","position":{"start":{"line":4,"column":130,"offset":143},"end":{"line":4,"column":174,"offset":187},"indent":[]},"value":"concept.mesh.resource.element.flow"},{"from":{"fname":"concept.mesh.resource.element.flow.snapshot.next","id":"yci31i07s3bwpl9jd2hptod","vaultName":"sflo"},"type":"backlink","position":{"start":{"line":2,"column":85,"offset":85},"end":{"line":2,"column":123,"offset":123},"indent":[]},"value":"concept.mesh.resource.element.flow"}],"anchors":{"relationship-to-node-flows":{"type":"header","text":"Relationship to node flows","value":"relationship-to-node-flows","line":16,"column":0,"depth":2},"relationship-pattern":{"type":"header","text":"Relationship pattern:","value":"relationship-pattern","line":20,"column":0,"depth":3},"ontology-example":{"type":"header","text":"Ontology Example","value":"ontology-example","line":29,"column":0,"depth":3},"persistent-identity":{"type":"header","text":"Persistent Identity","value":"persistent-identity","line":48,"column":0,"depth":2}},"children":["kr1y9tt3qljsbfy8lxm3u1g","9j8lhoyb0xkhg926nafgkai","0y6p8e594peoult03gobm94","9bu4sgma5c54bmwyl6ofg4c","8t3swuswoi81yuzo2bnecy9","sif626tmt3mw3nir5gv1s1a"],"parent":"9c27yly4ed3ju7msf8luhge","data":{}}
