{"id":"yxn5rsqsv2gq4s6wbnxsjsj","title":" Now","desc":"","updated":1755716895653,"created":1755715411842,"custom":{},"fname":"now","type":"note","vault":{"fsPath":"documentation","selfContained":false,"name":"sflo"},"contentHash":"6931bfe1a1c1b27f1a41ef87b299f834","links":[{"from":{"fname":"root","id":"voy7zrf0f6bs86m02uadhaf","vaultName":"sflo"},"type":"backlink","position":{"start":{"line":4,"column":1,"offset":107},"end":{"line":4,"column":8,"offset":114},"indent":[]},"value":"now"}],"anchors":{},"children":[],"parent":"voy7zrf0f6bs86m02uadhaf","data":{}}
